tree_compress/__init__.py
tree_compress/compress.cpython-310-x86_64-linux-gnu.so
tree_compress/compress.pyi
tree_compress/forestprune_addtree.py
tree_compress/forestprune_original.py
tree_compress/rebuild.py
tree_compress/util.py
lop_compress-1.0.0.dist-info/LICENSE
lop_compress-1.0.0.dist-info/METADATA
lop_compress-1.0.0.dist-info/WHEEL
lop_compress-1.0.0.dist-info/top_level.txt
lop_compress-1.0.0.dist-info/RECORD
