Metadata-Version: 2.1
Name: lop-compress
Version: 1.0.0
Summary: Compressing Tree Ensembles through Level-wise Optimization and Pruning
Author: Laurens Devos, Timo Martens
Project-URL: Homepage, https://github.com/ML-KULeuven/lop_compress
Project-URL: Issues, https://github.com/ML-KULeuven/lop_compress/issues
Classifier: Programming Language :: Python :: 3
Classifier: License :: OSI Approved :: Apache Software License
Classifier: Operating System :: OS Independent
Requires-Python: >=3.8
License-File: LICENSE
Requires-Dist: numpy>=1.26
Requires-Dist: scikit-learn>=1.4
Requires-Dist: scipy>=1.12
Requires-Dist: dtai-veritas>=0.2
Requires-Dist: colorama
